{"character_id":8,"state":{"connection":0.611003850575,"pride":0.00430221675,"valence":0.14282963875,"arousal":-0.05,"immersion":0.0,"last_chat_message_id":291,"last_chat_content":"你最喜欢的食物是什么？","last_chat_at":"2026-06-30T00:20:15.464865","user_status":"active","activity_type":"none","activity_label":null,"last_tick_at":"2026-06-30T00:20:39.820380+00:00","last_delta":{"pride":0.0,"connection":0.6},"total_ticks":3,"total_contact_triggers":1,"total_activity_triggers":0,"total_observation_triggers":1},"summary":"[积温] c:0.61(坐不住) p:0.00(中性) v:0.14(中性) a:-0.05(平静) i:0.00(无活动) | userStatus: active"}